LICENSE.txt
MANIFEST.in
README.md
setup.py
recurfaces/__init__.py
recurfaces/recurface.py
recurfaces/renderpipeline.py
recurfaces.egg-info/PKG-INFO
recurfaces.egg-info/SOURCES.txt
recurfaces.egg-info/dependency_links.txt
recurfaces.egg-info/requires.txt
recurfaces.egg-info/top_level.txt