Metadata-Version: 2.1
Name: recurfaces
Version: 4.0.0
Summary: A pygame framework used to organise Surfaces into a chain structure
Home-page: https://github.com/immijimmi/recurfaces
Download-URL: https://github.com/immijimmi/recurfaces/archive/refs/tags/v4.0.0.tar.gz
Author: immijimmi
Author-email: immijimmi1@gmail.com
License: MIT
Keywords: ui,gui,graphical,user,interface,game
Classifier: Development Status :: 4 - Beta
Classifier: Intended Audience :: Developers
Classifier: Topic :: Software Development :: Libraries :: Application Frameworks
Classifier: Topic :: Software Development :: Libraries :: pygame
Classifier: License :: OSI Approved :: MIT License
Classifier: Programming Language :: Python :: 3.12
License-File: LICENSE.txt
Requires-Dist: pygame~=2.5.0
